MANIFEST.in
README.rst
setup.py
celery_once/__init__.py
celery_once/helpers.py
celery_once/tasks.py
celery_once.egg-info/PKG-INFO
celery_once.egg-info/SOURCES.txt
celery_once.egg-info/dependency_links.txt
celery_once.egg-info/requires.txt
celery_once.egg-info/top_level.txt
celery_once/backends/__init__.py
celery_once/backends/file.py
celery_once/backends/redis.py