Metadata-Version: 1.1
Name: celery_once
Version: 3.0.1
Summary: Allows you to prevent multiple execution and queuing of celery tasks.
Home-page: https://github.com/cameronmaske/celery-once
Author: Cameron Maske
Author-email: cameronmaske@gmail.com
License: BSD
Keywords: celery,mutex,once,lock,redis
Platform: UNKNOWN
Classifier: Intended Audience :: Developers
Classifier: License :: OSI Approved :: BSD License
Classifier: Natural Language :: English
Classifier: Programming Language :: Python :: 2
Classifier: Programming Language :: Python :: 2.6
Classifier: Programming Language :: Python :: 2.7
Classifier: Programming Language :: Python :: 3
Classifier: Programming Language :: Python :: 3.3
Classifier: Programming Language :: Python :: 3.4
Classifier: Topic :: System :: Distributed Computing
